good_package/__init__.py
good_package/good_package.py
good_package-0.1.dist-info/METADATA
good_package-0.1.dist-info/WHEEL
good_package-0.1.dist-info/top_level.txt
good_package-0.1.dist-info/RECORD
