Metadata-Version: 2.1
Name: good-package
Version: 0.1
Summary: A simple package that prints 'Hello, World!'
Home-page: UNKNOWN
Author: Your Name
Author-email: your.email@example.com
License: UNKNOWN
Platform: UNKNOWN
